{
  "default": ["E00"],
  "wink": ["E01"],
  "smile": ["E02"],
  "cry": ["E03"],
  "angry": ["E04"],
  "bewildered": ["E05"],
  "blink": ["E06"],
  "flaming": ["E07"],
  "blaze": ["E07"],
  "zzz": ["E08"],
  "sleepy": ["E08"],
  "doze": ["E08"],
  "drool": ["E08"],
  "tired": ["E08"],
  "cheers": ["E09"],
  "sweetness": ["E09"],
  "chu": ["E10"],
  "smoochies": ["E10"],
  "dam": ["E11"],
  "despair": ["E12"],
  "glitter": ["E13"],
  "hit": ["E14"],
  "hot": ["E15"],
  "hum": ["E16"],
  "sigh": ["E16"],
  "love": ["E17"],
  "oops": ["E18"],
  "pain": ["E19"],
  "troubled": ["E20"],
  "qBlue": ["E21"],
  "shine": ["E22"],
  "ray": ["E22"],
  "stunned": ["E23"],
  "vomit": ["E24"],
  "queasy": ["E24"]
}